pynetworking/Communication_client.py
pynetworking/Communication_general.py
pynetworking/Communication_server.py
pynetworking/Cryptography.py
pynetworking/Data.py
pynetworking/ID_management.py
pynetworking/Logging.py
pynetworking/Packets.py
pynetworking/__init__.py
pynetworking/client.py
pynetworking/common.py
pynetworking/interface.py
pynetworking/server.py
pynetworking/utils.py
pynetworking/core/Communication_client.py
pynetworking/core/Communication_general.py
pynetworking/core/Communication_server.py
pynetworking/core/Cryptography.py
pynetworking/core/Data.py
pynetworking/core/ID_management.py
pynetworking/core/Logging.py
pynetworking/core/Packets.py
pynetworking/core/__init__.py
pynetworking/core/global_data.py
pynetworking/core/utils.py
pynetworking/tests/__init__.py
pynetworking/tests/example_functions.py
pynetworking/tests/test_Communication.py
pynetworking/tests/test_byteStream.py
pynetworking/tests/test_edgecases.py
pynetworking/tests/test_idManager.py
pynetworking/tests/test_packets.py
pynetworking/tests/test_packing.py
pynetworking_examples/__init__.py
pynetworking_examples/client_interface_server/Client.py
pynetworking_examples/client_interface_server/Interface.py
pynetworking_examples/client_interface_server/Server.py
pynetworking_examples/client_interface_server/__init__.py
pynetworking_examples/single_file/__init__.py
pynetworking_examples/single_file/all_functionality.py
pynetworking_examples/single_file/echo_server.py
pynetworking-0.1.11.dist-info/LICENSE
pynetworking-0.1.11.dist-info/METADATA
pynetworking-0.1.11.dist-info/WHEEL
pynetworking-0.1.11.dist-info/top_level.txt
pynetworking-0.1.11.dist-info/RECORD
