Metadata-Version: 2.1
Name: pynetworking
Version: 0.1.11
Summary: High level network communication
Home-page: https://github.com/JulianSobott/pynetworking
Author: Julian Sobott
Author-email: julian.sobott@gmx.de
License: Apache
Project-URL: Bug Tracker, https://github.com/JulianSobott/pynetworking/issues
Project-URL: Documentation, http://pynetworking.readthedocs.io/
Project-URL: Source Code, https://github.com/JulianSobott/pynetworking
Keywords: network packet communication
Platform: UNKNOWN
Classifier: Programming Language :: Python :: 3.7
Classifier: License :: OSI Approved :: Apache Software License
Classifier: Operating System :: OS Independent
Classifier: Topic :: Software Development :: Libraries
Requires-Dist: cryptography
Requires-Dist: dill
